{
  "3735293": {
    "book_url": "https://www.goodreads.com/book/show/3735293",
    "title": "Clean Code: A Handbook of Agile Software Craftsmanship (Robert C. Martin Series)",
    "_id": "3735293",
    "ISBN": "0132350882",
    "author": "45372",
    "author_url": "https://goodreads.com/author/show/45372.Robert_C_Martin",
    "rating": "4.40",
    "rating_count": "14910",
    "review_count": "877",
    "image_url": "https://i.gr-assets.com/images/S/compressed.photo.goodreads.com/books/1436202607l/3735293._SX318_.jpg",
    "similar_books": [
      "85009",
      "44936",
      "58128",
      "4845",
      "34927404",
      "44919",
      "179133",
      "387190",
      "23215733",
      "2998152",
      "85012",
      "70156",
      "13629",
      "22512931",
      "127932",
      "67833",
      "6487349"
    ]
  },
  "85012": {
    "book_url": "https://www.goodreads.com/book/show/85012",
    "title": "Enterprise Integration Patterns: Designing, Building, and Deploying Messaging Solutions (The Addison-Wesley Signature Series)",
    "_id": "85012",
    "ISBN": "0321200683",
    "author": "48627",
    "author_url": "https://goodreads.com/author/show/48627.Gregor_Hohpe",
    "rating": "4.09",
    "rating_count": "1323",
    "review_count": "52",
    "image_url": "https://i.gr-assets.com/images/S/compressed.photo.goodreads.com/books/1347390905l/85012.jpg",
    "similar_books": [
      "85009",
      "34927404",
      "44936",
      "22512931",
      "23463279",
      "58128",
      "18043011",
      "4099",
      "44919",
      "1069827",
      "127932",
      "179133",
      "4845",
      "387190",
      "10284614",
      "108986",
      "4268826"
    ]
  },
  "13425570": {
    "book_url": "https://www.goodreads.com/book/show/13425570",
    "title": "How Will You Measure Your Life?",
    "_id": "13425570",
    "ISBN": "0062102427",
    "author": "1792",
    "author_url": "https://goodreads.com/author/show/1792.Clayton_M_Christensen",
    "rating": "4.08",
    "rating_count": "23732",
    "review_count": "2201",
    "image_url": "https://i.gr-assets.com/images/S/compressed.photo.goodreads.com/books/1328046792l/13425570.jpg",
    "similar_books": [
      "16158498",
      "16158494",
      "40121378",
      "41795733",
      "42398476",
      "42118073",
      "45020328",
      "12609433",
      "36462566",
      "23215490",
      "26156469",
      "34536488",
      "39704250",
      "39286958",
      "44063692",
      "43848929",
      "27220736"
    ]
  },
  "16158498": {
    "book_url": "https://www.goodreads.com/book/show/16158498",
    "title": "Give and Take: A Revolutionary Approach to Success",
    "_id": "16158498",
    "ISBN": "0670026557",
    "author": "6583155",
    "author_url": "https://goodreads.com/author/show/6583155.Adam_M_Grant",
    "rating": "4.10",
    "rating_count": "23243",
    "review_count": "1593",
    "image_url": "https://i.gr-assets.com/images/S/compressed.photo.goodreads.com/books/1356136579l/16158498.jpg",
    "similar_books": [
      "12609433",
      "7108725",
      "25744928",
      "13593553",
      "16144853",
      "84699",
      "6570502",
      "3860977",
      "76865",
      "32938155",
      "27213329",
      "26156469",
      "13425570",
      "41795733",
      "6452796",
      "40121378",
      "11468377"
    ]
  },
  "26156469": {
    "book_url": "https://www.goodreads.com/book/show/26156469",
    "title": "Never Split the Difference",
    "_id": "26156469",
    "ISBN": "0062407805",
    "author": "5525291",
    "author_url": "https://goodreads.com/author/show/5525291.Chris_Voss",
    "rating": "4.40",
    "rating_count": "56600",
    "review_count": "4205",
    "image_url": "https://i.gr-assets.com/images/S/compressed.photo.goodreads.com/books/1460910517l/26156469.jpg",
    "similar_books": [
      "28815",
      "7108725",
      "4865",
      "44525305",
      "27220736",
      "41721428",
      "23848190",
      "43848929",
      "11468377",
      "76865",
      "34536488",
      "18176747",
      "368593",
      "34466963",
      "69571",
      "3228917",
      "25744928"
    ]
  },
  "84983": {
    "book_url": "https://www.goodreads.com/book/show/84983",
    "title": "Agile Principles, Patterns, and Practices in C# (Robert C. Martin Series)",
    "_id": "84983",
    "ISBN": "0131857258",
    "author": "45372",
    "author_url": "https://goodreads.com/author/show/45372.Robert_C_Martin",
    "rating": "4.31",
    "rating_count": "697",
    "review_count": "32",
    "image_url": "https://i.gr-assets.com/images/S/compressed.photo.goodreads.com/books/1348657323l/84983.jpg",
    "similar_books": [
      "44936",
      "4099",
      "85041",
      "25531393",
      "58128",
      "387190",
      "13507787",
      "6707987",
      "18323583",
      "6487349",
      "4268826",
      "4845",
      "9407722",
      "7121415",
      "179133",
      "44919",
      "23215733"
    ]
  },
  "34536488": {
    "book_url": "https://www.goodreads.com/book/show/34536488",
    "title": "Principles: Life and Work",
    "_id": "34536488",
    "ISBN": "1508243247",
    "author": "5289593",
    "author_url": "https://goodreads.com/author/show/5289593.Ray_Dalio",
    "rating": "4.13",
    "rating_count": "31137",
    "review_count": "2034",
    "image_url": "https://i.gr-assets.com/images/S/compressed.photo.goodreads.com/books/1503365703l/34536488._SX318_.jpg",
    "similar_books": [
      "106835",
      "174713",
      "40121378",
      "23848190",
      "39286958",
      "27220736",
      "44525305",
      "31823677",
      "23014006",
      "11468377",
      "42118073",
      "242472",
      "18176747",
      "76865",
      "38315",
      "18050143",
      "28815"
    ]
  },
  "58128": {
    "book_url": "https://www.goodreads.com/book/show/58128",
    "title": "Head First Design Patterns",
    "_id": "58128",
    "ISBN": "0596007124",
    "author": "32731",
    "author_url": "https://goodreads.com/author/show/32731.Eric_Freeman",
    "rating": "4.28",
    "rating_count": "7133",
    "review_count": "404",
    "image_url": "https://i.gr-assets.com/images/S/compressed.photo.goodreads.com/books/1408309444l/58128.jpg",
    "similar_books": [
      "3735293",
      "44936",
      "4099",
      "34927404",
      "4845",
      "10284614",
      "70156",
      "127932",
      "44919",
      "2998152",
      "108986",
      "387190",
      "428588",
      "18043011",
      "179133",
      "12544648",
      "22847284"
    ]
  },
  "28815": {
    "book_url": "https://www.goodreads.com/book/show/28815",
    "title": " Influence: How and Why People Agree to Things",
    "_id": "28815",
    "ISBN": "006124189X",
    "author": "160932",
    "author_url": "https://goodreads.com/author/show/160932.Robert_B_Cialdini",
    "rating": "4.19",
    "rating_count": "100168",
    "review_count": "3662",
    "image_url": "https://i.gr-assets.com/images/S/compressed.photo.goodreads.com/books/1391026083l/28815.jpg",
    "similar_books": [
      "11468377",
      "30186948",
      "36072",
      "12609433",
      "368593",
      "106835",
      "4122",
      "69571",
      "7108725",
      "26156469",
      "4898",
      "76865",
      "1633",
      "18050143",
      "69242",
      "1303",
      "81948"
    ]
  },
  "15895832": {
    "book_url": "https://www.goodreads.com/book/show/15895832",
    "title": "Influence: Science and Practice - The Comic",
    "_id": "15895832",
    "ISBN": "161066020X",
    "author": "160932",
    "author_url": "https://goodreads.com/author/show/160932.Robert_B_Cialdini",
    "rating": "3.98",
    "rating_count": "464",
    "review_count": "28",
    "image_url": "https://i.gr-assets.com/images/S/compressed.photo.goodreads.com/books/1400092344l/15895832.jpg",
    "similar_books": [
      "22202",
      "6486483",
      "84525",
      "23019295",
      "17859574",
      "28012",
      "103408",
      "2439931",
      "7546",
      "857333",
      "141026",
      "13593553",
      "16158501",
      "11296523",
      "2158811",
      "7063297",
      "27157424"
    ]
  },
  "25744928": {
    "book_url": "https://www.goodreads.com/book/show/25744928",
    "title": "Deep Work",
    "_id": "25744928",
    "ISBN": "1455586692",
    "author": "147891",
    "author_url": "https://goodreads.com/author/show/147891.Cal_Newport",
    "rating": "4.20",
    "rating_count": "72179",
    "review_count": "6480",
    "image_url": "https://i.gr-assets.com/images/S/compressed.photo.goodreads.com/books/1447957962l/25744928._SY475_.jpg",
    "similar_books": [
      "18077875",
      "12609433",
      "34466963",
      "18668059",
      "368593",
      "44770129",
      "26156469",
      "27036528",
      "4865",
      "40745",
      "11468377",
      "18693655",
      "16256798",
      "1633",
      "66354",
      "36072",
      "43582733"
    ]
  },
  "372384": {
    "book_url": "https://www.goodreads.com/book/show/372384",
    "title": "The Final Detail",
    "_id": "372384",
    "ISBN": "0440225450",
    "author": "24689",
    "author_url": "https://goodreads.com/author/show/24689.Harlan_Coben",
    "rating": "4.03",
    "rating_count": "20494",
    "review_count": "886",
    "image_url": "https://i.gr-assets.com/images/S/compressed.photo.goodreads.com/books/1300230473l/372384.jpg",
    "similar_books": [
      "48985654",
      "44422464",
      "52752171",
      "25554820",
      "44016314",
      "43885041",
      "500757",
      "607410",
      "49123131",
      "41064227",
      "45157885",
      "43903354",
      "242202",
      "52669054",
      "84843",
      "32502",
      "38204677"
    ]
  },
  "2439931": {
    "book_url": "https://www.goodreads.com/book/show/2439931",
    "title": "Sniper One: The Blistering True Story of a British Battle Group Under Siege",
    "_id": "2439931",
    "ISBN": "0141029013",
    "author": "703662",
    "author_url": "https://goodreads.com/author/show/703662.Dan_Mills",
    "rating": "4.26",
    "rating_count": "4268",
    "review_count": "184",
    "image_url": "https://i.gr-assets.com/images/S/compressed.photo.goodreads.com/books/1312518053l/2439931.jpg",
    "similar_books": [
      "22202",
      "25663799",
      "4664989",
      "40088566",
      "14325926",
      "18339909",
      "3331263",
      "1049942",
      "34873461",
      "50793304",
      "144741",
      "23254689",
      "18890156",
      "35174194",
      "52332686",
      "19358992",
      "38586921"
    ]
  },
  "32938155": {
    "book_url": "https://www.goodreads.com/book/show/32938155",
    "title": "Option B: Facing Adversity, Building Resilience and Finding Joy",
    "_id": "32938155",
    "ISBN": "0753548283",
    "author": "5333595",
    "author_url": "https://goodreads.com/author/show/5333595.Sheryl_Sandberg",
    "rating": "3.87",
    "rating_count": "43816",
    "review_count": "3618",
    "image_url": "https://i.gr-assets.com/images/S/compressed.photo.goodreads.com/books/1493998427l/32938155._SY475_.jpg",
    "similar_books": [
      "16158498",
      "27213329",
      "40109367",
      "40776644",
      "35412097",
      "7155145",
      "52129515",
      "34565022",
      "43848929",
      "18505796",
      "6452796",
      "18077903",
      "15843166",
      "31423133",
      "13588356",
      "38746485",
      "23317538"
    ]
  },
  "179133": {
    "book_url": "https://www.goodreads.com/book/show/179133",
    "title": "Domain-Driven Design: Tackling Complexity in the Heart of Software",
    "_id": "179133",
    "ISBN": "0321125215",
    "author": "104368",
    "author_url": "https://goodreads.com/author/show/104368.Eric_Evans",
    "rating": "4.15",
    "rating_count": "4109",
    "review_count": "191",
    "image_url": "https://i.gr-assets.com/images/S/compressed.photo.goodreads.com/books/1287493789l/179133.jpg",
    "similar_books": [
      "44936",
      "70156",
      "15756865",
      "3735293",
      "85009",
      "387190",
      "22512931",
      "18043011",
      "28602719",
      "4099",
      "10284614",
      "4268826",
      "1069827",
      "67833",
      "34927404",
      "4845",
      "85041"
    ]
  },
  "253203": {
    "book_url": "https://www.goodreads.com/book/show/253203",
    "title": "How to Become a Straight-A Student",
    "_id": "253203",
    "ISBN": "0767922719",
    "author": "147891",
    "author_url": "https://goodreads.com/author/show/147891.Cal_Newport",
    "rating": "4.16",
    "rating_count": "5928",
    "review_count": "552",
    "image_url": "https://i.gr-assets.com/images/S/compressed.photo.goodreads.com/books/1361208630l/253203.jpg",
    "similar_books": [
      "18693655",
      "18770267",
      "44770129",
      "40121378",
      "36647421",
      "16250645",
      "17788725",
      "25733994",
      "22088715",
      "22571656",
      "18077875",
      "34507927",
      "19288640",
      "593497",
      "16158493",
      "25492416",
      "26312997"
    ]
  },
  "34927404": {
    "book_url": "https://www.goodreads.com/book/show/34927404",
    "title": "Effective Java Programming Language Guide",
    "_id": "34927404",
    "ISBN": "0134685997",
    "author": "60805",
    "author_url": "https://goodreads.com/author/show/60805.Joshua_Bloch",
    "rating": "4.50",
    "rating_count": "6621",
    "review_count": "355",
    "image_url": "https://i.gr-assets.com/images/S/compressed.photo.goodreads.com/books/1513389229l/34927404.jpg",
    "similar_books": [
      "3735293",
      "58128",
      "85009",
      "71672",
      "44936",
      "4099",
      "108986",
      "10284614",
      "4845",
      "20534354",
      "428588",
      "23463279",
      "70156",
      "44919",
      "231262",
      "179133",
      "29242249"
    ]
  },
  "84985": {
    "book_url": "https://www.goodreads.com/book/show/84985",
    "title": "Agile Software Development, Principles, Patterns, and Practices",
    "_id": "84985",
    "ISBN": "0135974445",
    "author": "45372",
    "author_url": "https://goodreads.com/author/show/45372.Robert_C_Martin",
    "rating": "4.24",
    "rating_count": "1172",
    "review_count": "48",
    "image_url": "https://i.gr-assets.com/images/S/compressed.photo.goodreads.com/books/1348196056l/84985.jpg",
    "similar_books": [
      "387190",
      "4099",
      "44919",
      "85009",
      "70156",
      "67833",
      "58128",
      "179133",
      "85041",
      "4845",
      "6399113",
      "85012",
      "13629",
      "4268826",
      "41793",
      "9267",
      "34927404"
    ]
  },
  "44063692": {
    "book_url": "https://www.goodreads.com/book/show/44063692",
    "title": "What You Do Is Who You Are",
    "_id": "44063692",
    "ISBN": "0062871331",
    "author": "7155094",
    "author_url": "https://goodreads.com/author/show/7155094.Ben_Horowitz",
    "rating": "4.06",
    "rating_count": "3498",
    "review_count": "345",
    "image_url": "https://i.gr-assets.com/images/S/compressed.photo.goodreads.com/books/1571347435l/44063692.jpg",
    "similar_books": [
      "42348376",
      "44525305",
      "38390751",
      "48691943",
      "43889703",
      "44573628",
      "38398157",
      "45733318",
      "45016225",
      "49099937",
      "44428950",
      "41795733",
      "43582733",
      "39863447",
      "50772888"
    ]
  },
  "1633": {
    "book_url": "https://www.goodreads.com/book/show/1633",
    "title": "Getting Things Done: How To Achieve Stress-free Productivity",
    "_id": "1633",
    "ISBN": "0142000280",
    "author": "1058",
    "author_url": "https://goodreads.com/author/show/1058.David_Allen",
    "rating": "3.99",
    "rating_count": "127497",
    "review_count": "5055",
    "image_url": "https://i.gr-assets.com/images/S/compressed.photo.goodreads.com/books/1312474060l/1633.jpg",
    "similar_books": [
      "368593",
      "30186948",
      "12609433",
      "4865",
      "4122",
      "28815",
      "7108725",
      "69571",
      "76865",
      "69242",
      "81948",
      "4894",
      "6732019",
      "4898",
      "10127019",
      "21343",
      "18050143"
    ]
  },
  "6570502": {
    "book_url": "https://www.goodreads.com/book/show/6570502",
    "title": "Switch: How to Change Things When Change Is Hard",
    "_id": "6570502",
    "ISBN": "0385528752",
    "author": "39021",
    "author_url": "https://goodreads.com/author/show/39021.Chip_Heath",
    "rating": "4.04",
    "rating_count": "42355",
    "review_count": "2834",
    "image_url": "https://i.gr-assets.com/images/S/compressed.photo.goodreads.com/books/1422839688l/6570502.jpg",
    "similar_books": [
      "6452796",
      "48549702",
      "16158498",
      "12609433",
      "50937",
      "76865",
      "8310410",
      "52108340",
      "7108725",
      "40745",
      "38390751",
      "22668729",
      "40121378",
      "21343",
      "84699",
      "18406657",
      "129731"
    ]
  },
  "69242": {
    "book_url": "https://www.goodreads.com/book/show/69242",
    "title": "Made to Stick: Why Some Ideas Survive and Others Die",
    "_id": "69242",
    "ISBN": "1400064287",
    "author": "39021",
    "author_url": "https://goodreads.com/author/show/39021.Chip_Heath",
    "rating": "3.96",
    "rating_count": "73945",
    "review_count": "2701",
    "image_url": "https://i.gr-assets.com/images/S/compressed.photo.goodreads.com/books/1402600211l/69242.jpg",
    "similar_books": [
      "2615",
      "81948",
      "7108725",
      "1633",
      "76865",
      "28815",
      "12609433",
      "2612",
      "4898",
      "6452796",
      "368593",
      "6732019",
      "16071764",
      "18050143",
      "18077903",
      "30186948",
      "10127019"
    ]
  },
  "3487850": {
    "book_url": "https://www.goodreads.com/book/show/3487850",
    "title": "The Innovator's Prescription: A Disruptive Solution for Health Care",
    "_id": "3487850",
    "ISBN": "0071592083",
    "author": "1792",
    "author_url": "https://goodreads.com/author/show/1792.Clayton_M_Christensen",
    "rating": "4.21",
    "rating_count": "925",
    "review_count": "79",
    "image_url": "https://i.gr-assets.com/images/S/compressed.photo.goodreads.com/books/1347670006l/3487850.jpg",
    "similar_books": [
      "31253737",
      "22825546",
      "40915762",
      "29974755",
      "12428512",
      "42585168",
      "34267304",
      "23131174",
      "18667990",
      "40886652",
      "15824358",
      "52300107",
      "134777",
      "21535014",
      "11547245",
      "11994353",
      "20763745"
    ]
  },
  "36072": {
    "book_url": "https://www.goodreads.com/book/show/36072",
    "title": "The 7 Habits of Highly Effective People",
    "_id": "36072",
    "ISBN": "0743269519",
    "author": "1538",
    "author_url": "https://goodreads.com/author/show/1538.Stephen_R_Covey",
    "rating": "4.12",
    "rating_count": "519806",
    "review_count": "10341",
    "image_url": "https://i.gr-assets.com/images/S/compressed.photo.goodreads.com/books/1421842784l/36072.jpg",
    "similar_books": [
      "69571",
      "30186948",
      "368593",
      "12609433",
      "4894",
      "7108725",
      "2612",
      "18050143",
      "3228917",
      "76865",
      "10127019",
      "11468377",
      "52529",
      "1134122",
      "28257707",
      "1202",
      "11084145"
    ]
  },
  "11084145": {
    "book_url": "https://www.goodreads.com/book/show/11084145",
    "title": "Steve Jobs",
    "_id": "11084145",
    "ISBN": "1451648537",
    "author": "7111",
    "author_url": "https://goodreads.com/author/show/7111.Walter_Isaacson",
    "rating": "4.14",
    "rating_count": "949500",
    "review_count": "18379",
    "image_url": "https://i.gr-assets.com/images/S/compressed.photo.goodreads.com/books/1511288482l/11084145._SY475_.jpg",
    "similar_books": [
      "48855",
      "8664353",
      "2203",
      "1202",
      "4865",
      "9151181",
      "36072",
      "18050143",
      "2612",
      "69571",
      "10127019",
      "17851885",
      "9021",
      "30186948",
      "11468377",
      "3228917",
      "27220736"
    ]
  },
  "2612": {
    "book_url": "https://www.goodreads.com/book/show/2612",
    "title": "The Tipping Point: How Little Things Can Make a Big Difference",
    "_id": "2612",
    "ISBN": "0316346624",
    "author": "1439",
    "author_url": "https://goodreads.com/author/show/1439.Malcolm_Gladwell",
    "rating": "3.97",
    "rating_count": "686673",
    "review_count": "13529",
    "image_url": "https://i.gr-assets.com/images/S/compressed.photo.goodreads.com/books/1473396980l/2612._SY475_.jpg",
    "similar_books": [
      "10127019",
      "4865",
      "18050143",
      "36072",
      "368593",
      "11468377",
      "11084145",
      "7108725",
      "6732019",
      "28257707",
      "69571",
      "12609433",
      "6402364",
      "76865",
      "4894",
      "23692271",
      "18176747"
    ]
  },
  "873375": {
    "book_url": "https://www.goodreads.com/book/show/873375",
    "title": "UML for Java Programmers (Robert C. Martin)",
    "_id": "873375",
    "ISBN": "0131428489",
    "author": "45372",
    "author_url": "https://goodreads.com/author/show/45372.Robert_C_Martin",
    "rating": "3.63",
    "rating_count": "38",
    "review_count": "1",
    "image_url": "https://i.gr-assets.com/images/S/compressed.photo.goodreads.com/books/1348858361l/873375.jpg",
    "similar_books": [
      "41913360",
      "13663747",
      "1641865",
      "944860"
    ]
  },
  "44919": {
    "book_url": "https://www.goodreads.com/book/show/44919",
    "title": "Working Effectively with Legacy Code",
    "_id": "44919",
    "ISBN": "0131177052",
    "author": "25201",
    "author_url": "https://goodreads.com/author/show/25201.Michael_C_Feathers",
    "rating": "4.14",
    "rating_count": "3918",
    "review_count": "224",
    "image_url": "https://i.gr-assets.com/images/S/compressed.photo.goodreads.com/books/1348627451l/44919.jpg",
    "similar_books": [
      "387190",
      "179133",
      "3735293",
      "10284614",
      "18043011",
      "4099",
      "85009",
      "4268826",
      "67833",
      "70156",
      "4845",
      "58128",
      "1069827",
      "13629",
      "34927404",
      "8686650",
      "85041"
    ]
  },
  "387190": {
    "book_url": "https://www.goodreads.com/book/show/387190",
    "title": "Test Driven Development: By Example",
    "_id": "387190",
    "ISBN": "0321146530",
    "author": "25211",
    "author_url": "https://goodreads.com/author/show/25211.Kent_Beck",
    "rating": "4.08",
    "rating_count": "3564",
    "review_count": "168",
    "image_url": "https://i.gr-assets.com/images/S/compressed.photo.goodreads.com/books/1372039943l/387190.jpg",
    "similar_books": [
      "44919",
      "85009",
      "3735293",
      "179133",
      "18043011",
      "10284614",
      "4099",
      "58128",
      "70156",
      "4845",
      "45280021",
      "85041",
      "8686650",
      "1069827",
      "34927404",
      "22512931",
      "6399113"
    ]
  },
  "50937": {
    "book_url": "https://www.goodreads.com/book/show/50937",
    "title": "First, Break All the Rules: What the World's Greatest Managers Do Differently ",
    "_id": "50937",
    "ISBN": "0684852861",
    "author": "18731",
    "author_url": "https://goodreads.com/author/show/18731.Marcus_Buckingham",
    "rating": "3.93",
    "rating_count": "35626",
    "review_count": "667",
    "image_url": "https://i.gr-assets.com/images/S/compressed.photo.goodreads.com/books/1442357545l/50937._SY475_.jpg",
    "similar_books": [
      "763362",
      "48019",
      "108444",
      "1635",
      "15014",
      "866222",
      "3828382",
      "84699",
      "2467566",
      "4191136",
      "21343",
      "2615",
      "84525",
      "48016",
      "61329",
      "4122",
      "106835"
    ]
  },
  "127932": {
    "book_url": "https://www.goodreads.com/book/show/127932",
    "title": "Java Concurrency in Practice",
    "_id": "127932",
    "ISBN": "0321349601",
    "author": "73409",
    "author_url": "https://goodreads.com/author/show/73409.Brian_Goetz",
    "rating": "4.46",
    "rating_count": "2447",
    "review_count": "120",
    "image_url": "https://i.gr-assets.com/images/S/compressed.photo.goodreads.com/books/1349044077l/127932.jpg",
    "similar_books": [
      "85009",
      "44936",
      "58128",
      "3735293",
      "70156",
      "22512931",
      "23463279",
      "10284614",
      "4099",
      "179133",
      "71672",
      "12544648",
      "428588",
      "4845",
      "18043011",
      "108986",
      "515601"
    ]
  },
  "84843": {
    "book_url": "https://www.goodreads.com/book/show/84843",
    "title": "Kill the Messenger",
    "_id": "84843",
    "ISBN": "0553583581",
    "author": "9890",
    "author_url": "https://goodreads.com/author/show/9890.Tami_Hoag",
    "rating": "3.84",
    "rating_count": "8693",
    "review_count": "491",
    "image_url": "https://i.gr-assets.com/images/S/compressed.photo.goodreads.com/books/1320483123l/84843.jpg",
    "similar_books": [
      "607410",
      "31494455",
      "242202",
      "50251836",
      "44322945",
      "53218497",
      "53870242",
      "42098615",
      "51362",
      "52838845",
      "58080",
      "44146329",
      "27803344",
      "6530",
      "53913861",
      "69625",
      "40224966"
    ]
  },
  "16158493": {
    "book_url": "https://www.goodreads.com/book/show/16158493",
    "title": "The First 20 Hours: How to Learn Anything...Fast",
    "_id": "16158493",
    "ISBN": "1591845556",
    "author": "4409125",
    "author_url": "https://goodreads.com/author/show/4409125.Josh_Kaufman",
    "rating": "3.49",
    "rating_count": "4968",
    "review_count": "536",
    "image_url": "https://i.gr-assets.com/images/S/compressed.photo.goodreads.com/books/1364771935l/16158493.jpg",
    "similar_books": [
      "14891980",
      "30335551",
      "227552",
      "18079767",
      "44770129",
      "37774244",
      "13589182",
      "18482790",
      "12601615",
      "27139721",
      "18667813",
      "13525945",
      "18085519",
      "34507927",
      "30038905",
      "25744928",
      "35211"
    ]
  },
  "4122": {
    "book_url": "https://www.goodreads.com/book/show/4122",
    "title": "Built to Last: Successful Habits of Visionary Companies",
    "_id": "4122",
    "ISBN": "0060566108",
    "author": "2826",
    "author_url": "https://goodreads.com/author/show/2826.James_C_Collins",
    "rating": "4.01",
    "rating_count": "59642",
    "review_count": "676",
    "image_url": "https://i.gr-assets.com/images/S/compressed.photo.goodreads.com/books/1412047084l/4122.jpg",
    "similar_books": [
      "21343",
      "7108725",
      "69242",
      "81948",
      "28815",
      "36072",
      "1633",
      "18077903",
      "30186948",
      "2615",
      "2612",
      "4894",
      "6828896",
      "113934",
      "4865",
      "10127019",
      "6452796"
    ]
  },
  "866222": {
    "book_url": "https://www.goodreads.com/book/show/866222",
    "title": "Winning",
    "_id": "866222",
    "ISBN": "0060753943",
    "author": "3770",
    "author_url": "https://goodreads.com/author/show/3770.Jack_Welch",
    "rating": "3.84",
    "rating_count": "38433",
    "review_count": "746",
    "image_url": "https://i.gr-assets.com/images/S/compressed.photo.goodreads.com/books/1366775828l/866222.jpg",
    "similar_books": [
      "76865",
      "1635",
      "815716",
      "4122",
      "763362",
      "48019",
      "1911",
      "4898",
      "50937",
      "36072",
      "12675109",
      "407999",
      "56454",
      "1044141",
      "106835",
      "181206",
      "33449"
    ]
  },
  "7108725": {
    "book_url": "https://www.goodreads.com/book/show/7108725",
    "title": "Start with Why: How Great Leaders Inspire Everyone to Take Action",
    "_id": "7108725",
    "ISBN": "1591842808",
    "author": "3158574",
    "author_url": "https://goodreads.com/author/show/3158574.Simon_Sinek",
    "rating": "4.09",
    "rating_count": "119599",
    "review_count": "5964",
    "image_url": "https://i.gr-assets.com/images/S/compressed.photo.goodreads.com/books/1360936414l/7108725.jpg",
    "similar_books": [
      "4865",
      "368593",
      "69571",
      "18050143",
      "76865",
      "30186948",
      "10127019",
      "6732019",
      "12609433",
      "18176747",
      "2612",
      "4122",
      "81948",
      "3228917",
      "4894",
      "40121378",
      "28815"
    ]
  },
  "8308501": {
    "book_url": "https://www.goodreads.com/book/show/8308501",
    "title": "HBR's 10 Must Reads on Managing Yourself ",
    "_id": "8308501",
    "ISBN": "1422157997",
    "author": "1792",
    "author_url": "https://goodreads.com/author/show/1792.Clayton_M_Christensen",
    "rating": "4.03",
    "rating_count": "3145",
    "review_count": "242",
    "image_url": "https://i.gr-assets.com/images/S/compressed.photo.goodreads.com/books/1344703933l/8308501.jpg",
    "similar_books": [
      "8376716",
      "23258980",
      "9612515",
      "9004246",
      "15824367",
      "36133333",
      "8414509",
      "15824365",
      "15824364",
      "31945262",
      "15824366",
      "13586942",
      "13586938",
      "25159545",
      "39793332",
      "44793413",
      "27038055"
    ]
  },
  "85009": {
    "book_url": "https://www.goodreads.com/book/show/85009",
    "title": "Design Patterns: Elements of Reusable Object-Oriented Software (Addison-Wesley Professional Computing Series)",
    "_id": "85009",
    "ISBN": "0201633612",
    "author": "48622",
    "author_url": "https://goodreads.com/author/show/48622.Erich_Gamma",
    "rating": "4.18",
    "rating_count": "9848",
    "review_count": "351",
    "image_url": "https://i.gr-assets.com/images/S/compressed.photo.goodreads.com/books/1348027904l/85009.jpg",
    "similar_books": [
      "44936",
      "4099",
      "58128",
      "4845",
      "387190",
      "515601",
      "70156",
      "105125",
      "108986",
      "10284614",
      "179133",
      "34927404",
      "44919",
      "127932",
      "18043011",
      "112251",
      "2998152"
    ]
  },
  "18050143": {
    "book_url": "https://www.goodreads.com/book/show/18050143",
    "title": "Zero to One: Notes on Start Ups, or How to Build the Future",
    "_id": "18050143",
    "ISBN": "0804139296",
    "author": "8474721",
    "author_url": "https://goodreads.com/author/show/8474721.Peter_Thiel",
    "rating": "4.17",
    "rating_count": "185794",
    "review_count": "5813",
    "image_url": "https://i.gr-assets.com/images/S/compressed.photo.goodreads.com/books/1414347376l/18050143.jpg",
    "similar_books": [
      "4865",
      "18176747",
      "2612",
      "368593",
      "7723797",
      "22668729",
      "25541028",
      "13078769",
      "36072",
      "98233",
      "1134122",
      "11468377",
      "763362",
      "69571",
      "43848929",
      "30186948",
      "7108725"
    ]
  },
  "1049942": {
    "book_url": "https://www.goodreads.com/book/show/1049942",
    "title": "Immediate Action",
    "_id": "1049942",
    "ISBN": "0440222451",
    "author": "12673",
    "author_url": "https://goodreads.com/author/show/12673.Andy_McNab",
    "rating": "3.95",
    "rating_count": "3110",
    "review_count": "74",
    "image_url": "https://i.gr-assets.com/images/S/compressed.photo.goodreads.com/books/1320439282l/1049942.jpg",
    "similar_books": [
      "2439931",
      "18890156",
      "1144470",
      "41065587",
      "144741",
      "63699",
      "52332686",
      "447089",
      "7333058",
      "1299333",
      "3331263",
      "18710805",
      "23254689",
      "18693609",
      "51071",
      "33848665",
      "21853661"
    ]
  },
  "81948": {
    "book_url": "https://www.goodreads.com/book/show/81948",
    "title": "The E-Myth Revisited: Why Most Small Businesses Don't Work and What to Do About It",
    "_id": "81948",
    "ISBN": "0887307280",
    "author": "3416",
    "author_url": "https://goodreads.com/author/show/3416.Michael_E_Gerber",
    "rating": "4.02",
    "rating_count": "61520",
    "review_count": "1963",
    "image_url": "https://i.gr-assets.com/images/S/compressed.photo.goodreads.com/books/1435673032l/81948._SY475_.jpg",
    "similar_books": [
      "2615",
      "30186948",
      "7108725",
      "4865",
      "4122",
      "69571",
      "10127019",
      "36072",
      "69242",
      "18050143",
      "76865",
      "6732019",
      "4898",
      "18176747",
      "33449",
      "115491",
      "1633"
    ]
  },
  "6623727": {
    "book_url": "https://www.goodreads.com/book/show/6623727",
    "title": "The E-Myth Enterprise: How to Turn A Great Idea Into a Thriving Business",
    "_id": "6623727",
    "ISBN": "0061733695",
    "author": "3416",
    "author_url": "https://goodreads.com/author/show/3416.Michael_E_Gerber",
    "rating": "3.67",
    "rating_count": "407",
    "review_count": "50",
    "image_url": "https://i.gr-assets.com/images/S/compressed.photo.goodreads.com/books/1348041856l/6623727.jpg",
    "similar_books": [
      "22103881",
      "40392296",
      "16256798",
      "160830",
      "31187115",
      "52290273",
      "3851617",
      "48907468",
      "1253",
      "34460583",
      "53308696",
      "15898640",
      "6985953",
      "4837266",
      "37875",
      "54143679"
    ]
  },
  "69625": {
    "book_url": "https://www.goodreads.com/book/show/69625",
    "title": "Early Autumn",
    "_id": "69625",
    "ISBN": "0440122147",
    "author": "397",
    "author_url": "https://goodreads.com/author/show/397.Robert_B_Parker",
    "rating": "4.12",
    "rating_count": "6945",
    "review_count": "410",
    "image_url": "https://i.gr-assets.com/images/S/compressed.photo.goodreads.com/books/1420794354l/69625.jpg",
    "similar_books": [
      "13573363",
      "17707636",
      "29093235",
      "37855535",
      "20821292",
      "34158336",
      "24612102",
      "410725",
      "48563877",
      "50359504",
      "43381651",
      "50871343",
      "500757",
      "48985654",
      "39709484",
      "50023815",
      "18079589"
    ]
  },
  "4099": {
    "book_url": "https://www.goodreads.com/book/show/4099",
    "title": "The Pragmatic Programmer: From Journeyman to Master",
    "_id": "4099",
    "ISBN": "020161622X",
    "author": "2815",
    "author_url": "https://goodreads.com/author/show/2815.Andy_Hunt",
    "rating": "4.32",
    "rating_count": "15727",
    "review_count": "910",
    "image_url": "https://i.gr-assets.com/images/S/compressed.photo.goodreads.com/books/1401432508l/4099.jpg",
    "similar_books": [
      "85009",
      "4845",
      "44936",
      "10284614",
      "58128",
      "13629",
      "44919",
      "67833",
      "18043011",
      "2998152",
      "34927404",
      "387190",
      "179133",
      "6399113",
      "43713",
      "23232941",
      "515601"
    ]
  },
  "18482790": {
    "book_url": "https://www.goodreads.com/book/show/18482790",
    "title": "La Tecnica del Pomodoro",
    "_id": "18482790",
    "ISBN": "3981567900",
    "author": "3318670",
    "author_url": "https://goodreads.com/author/show/3318670.Francesco_Cirillo",
    "rating": "3.73",
    "rating_count": "1426",
    "review_count": "204",
    "image_url": "https://i.gr-assets.com/images/S/compressed.photo.goodreads.com/books/1378948919l/18482790.jpg",
    "similar_books": [
      "25330220",
      "36898661",
      "49020941",
      "35754803",
      "53071025",
      "22693241",
      "24040556",
      "181210",
      "15819474",
      "25991058",
      "10419045",
      "44028717",
      "45895363",
      "227552",
      "16158493",
      "44525871",
      "43800984"
    ]
  },
  "17851885": {
    "book_url": "https://www.goodreads.com/book/show/17851885",
    "title": "I Am Malala: The Girl Who Stood Up for Education and Was Shot by the Taliban",
    "_id": "17851885",
    "ISBN": "0316322407",
    "author": "7064545",
    "author_url": "https://goodreads.com/author/show/7064545.Malala_Yousafzai",
    "rating": "4.12",
    "rating_count": "415447",
    "review_count": "20651",
    "image_url": "https://i.gr-assets.com/images/S/compressed.photo.goodreads.com/books/1375414895l/17851885.jpg",
    "similar_books": [
      "9021",
      "10884",
      "92057",
      "11084145",
      "38746485",
      "10883",
      "7968243",
      "112803",
      "19501",
      "25541028",
      "8664353",
      "1845",
      "88061",
      "2203",
      "9418327",
      "29780253",
      "13214"
    ]
  },
  "46182": {
    "book_url": "https://www.goodreads.com/book/show/46182",
    "title": "In Watermelon Sugar",
    "_id": "46182",
    "ISBN": "0099437597",
    "author": "7970",
    "author_url": "https://goodreads.com/author/show/7970.Richard_Brautigan",
    "rating": "3.99",
    "rating_count": "13135",
    "review_count": "1031",
    "image_url": "https://i.gr-assets.com/images/S/compressed.photo.goodreads.com/books/1482476781l/46182._SY475_.jpg",
    "similar_books": [
      "253945",
      "13153370",
      "23534",
      "29907849",
      "143732",
      "2223313",
      "15845811",
      "886605",
      "49508994",
      "1184218",
      "11291530",
      "151322",
      "11297",
      "576011",
      "13267597",
      "9568613",
      "43242169"
    ]
  },
  "3331263": {
    "book_url": "https://www.goodreads.com/book/show/3331263",
    "title": "Apache Dawn",
    "_id": "3331263",
    "ISBN": "1847442544",
    "author": "103951",
    "author_url": "https://goodreads.com/author/show/103951.Damien_Lewis",
    "rating": "4.13",
    "rating_count": "546",
    "review_count": "33",
    "image_url": "https://i.gr-assets.com/images/S/compressed.photo.goodreads.com/books/1356150873l/3331263.jpg",
    "similar_books": [
      "23254689",
      "4664989",
      "26109393",
      "40088566",
      "18963342",
      "22202",
      "6856897",
      "19358992",
      "14325926",
      "23787705",
      "19014556",
      "1049942",
      "728849",
      "6409733",
      "7719667",
      "1299333",
      "26805928"
    ]
  },
  "160588": {
    "book_url": "https://www.goodreads.com/book/show/160588",
    "title": "The Abortion: An Historical Romance 1966",
    "_id": "160588",
    "ISBN": "0224007793",
    "author": "7970",
    "author_url": "https://goodreads.com/author/show/7970.Richard_Brautigan",
    "rating": "4.00",
    "rating_count": "5355",
    "review_count": "381",
    "image_url": "https://i.gr-assets.com/images/S/compressed.photo.goodreads.com/books/1547292359l/160588._SY475_.jpg",
    "similar_books": [
      "18209522",
      "11959268",
      "53711988",
      "53809405",
      "6130588",
      "7509306",
      "403541",
      "38318351",
      "32815566",
      "45010932",
      "25572095",
      "39319507",
      "44322988",
      "44166567",
      "258945",
      "7062595",
      "13501978"
    ]
  },
  "2615": {
    "book_url": "https://www.goodreads.com/book/show/2615",
    "title": "The Innovator's Dilemma: The Revolutionary Book that Will Change the Way You Do Business (Collins Business Essentials)",
    "_id": "2615",
    "ISBN": "0060521996",
    "author": "1792",
    "author_url": "https://goodreads.com/author/show/1792.Clayton_M_Christensen",
    "rating": "4.01",
    "rating_count": "39544",
    "review_count": "1123",
    "image_url": "https://i.gr-assets.com/images/S/compressed.photo.goodreads.com/books/1347654027l/2615.jpg",
    "similar_books": [
      "41653",
      "18176747",
      "10127019",
      "69242",
      "114841",
      "18050143",
      "4898",
      "4122",
      "61329",
      "7108725",
      "76865",
      "368593",
      "18077903",
      "12609433",
      "1202",
      "30186948",
      "4865"
    ]
  }
}
